hyperon_das/__init__.py
hyperon_das/api.py
hyperon_das/exceptions.py
hyperon_das/factory.py
hyperon_das/logger.py
hyperon_das/pattern_matcher/__init__.py
hyperon_das/pattern_matcher/constants.py
hyperon_das/pattern_matcher/pattern_matcher.py
hyperon_das/utils.py
98ce1b5f404a2dfa601423fb0f12c09b98ce1b5f404a2dfa601423fb0f12c09bmain-0.1.1.dist-info/METADATA
98ce1b5f404a2dfa601423fb0f12c09b98ce1b5f404a2dfa601423fb0f12c09bmain-0.1.1.dist-info/WHEEL
98ce1b5f404a2dfa601423fb0f12c09b98ce1b5f404a2dfa601423fb0f12c09bmain-0.1.1.dist-info/RECORD
