Metadata-Version: 2.1
Name: 98ce1b5f404a2dfa601423fb0f12c09b98ce1b5f404a2dfa601423fb0f12c09bmain
Version: 0.1.1
Summary: Query Engine API for Distributed AtomSpace
Author: marcocapozzoli
Author-email: marcocapozzoli90@gmail.com
Requires-Python: >=3.8.5,<4.0.0
Classifier: Programming Language :: Python :: 3
Classifier: Programming Language :: Python :: 3.9
Classifier: Programming Language :: Python :: 3.10
Classifier: Programming Language :: Python :: 3.11
Requires-Dist: 98ce1b5f404a2dfa601423fb0f12c09b98ce1b5f404a2dfa601423fb0f12c09b (>=0.1.0,<0.2.0)
Requires-Dist: python-dotenv (>=1.0.0,<2.0.0)
